asposepdf/Absorbers.py
asposepdf/Api.py
asposepdf/Assist.py
asposepdf/Device.py
asposepdf/Facade.py
asposepdf/Forms.py
asposepdf/PdfFileEditor.py
asposepdf/__init__.py
asposepdf/generator/BaseParagraph.py
asposepdf/generator/Rectangle.py
asposepdf/generator/__init__.py
asposepdf/jlib/aspose.pdf-python-24.9.jar
asposepdf/pdf/AFRelationship.py
asposepdf/pdf/AbsorbedCell.py
asposepdf/pdf/AbsorbedRow.py
asposepdf/pdf/AbsorbedTable.py
asposepdf/pdf/ActionCollection.py
asposepdf/pdf/Annotation.py
asposepdf/pdf/AnnotationActionCollection.py
asposepdf/pdf/AnnotationSelector.py
asposepdf/pdf/AnnotationState.py
asposepdf/pdf/AnnotationStateModel.py
asposepdf/pdf/AppearanceDictionary.py
asposepdf/pdf/ApsLoadOptions.py
asposepdf/pdf/ApsSaveOptions.py
asposepdf/pdf/ApsToFlowConverter.py
asposepdf/pdf/Artifact.py
asposepdf/pdf/ArtifactCollection.py
asposepdf/pdf/Artifact_ArtifactSubtype.py
asposepdf/pdf/Artifact_ArtifactType.py
asposepdf/pdf/BackgroundArtifact.py
asposepdf/pdf/BarcodeField.py
asposepdf/pdf/BaseActionCollection.py
asposepdf/pdf/BaseOperatorCollection.py
asposepdf/pdf/BaseParagraph.py
asposepdf/pdf/BleedMarkAnnotation.py
asposepdf/pdf/Border.py
asposepdf/pdf/BorderCornerStyle.py
asposepdf/pdf/BorderEffect.py
asposepdf/pdf/BorderInfo.py
asposepdf/pdf/BorderSide.py
asposepdf/pdf/BorderStyle.py
asposepdf/pdf/BorderStyleConverter.py
asposepdf/pdf/BoxStyle.py
asposepdf/pdf/Brush.py
asposepdf/pdf/BuildVersionInfo.py
asposepdf/pdf/ButtonField.py
asposepdf/pdf/CapStyle.py
asposepdf/pdf/CaptionPosition.py
asposepdf/pdf/CaretAnnotation.py
asposepdf/pdf/CaretSymbol.py
asposepdf/pdf/CaretSymbolConverter.py
asposepdf/pdf/CdrLoadOptions.py
asposepdf/pdf/Cell.py
asposepdf/pdf/Cells.py
asposepdf/pdf/CgmImportOptions.py
asposepdf/pdf/CgmLoadOptions.py
asposepdf/pdf/CharInfo.py
asposepdf/pdf/CharInfoCollection.py
asposepdf/pdf/Characteristics.py
asposepdf/pdf/CheckboxField.py
asposepdf/pdf/CircleAnnotation.py
asposepdf/pdf/Collection.py
asposepdf/pdf/CollectionField.py
aspose_pdf_for_python_via_java-24.9.dist-info/METADATA
aspose_pdf_for_python_via_java-24.9.dist-info/WHEEL
aspose_pdf_for_python_via_java-24.9.dist-info/top_level.txt
aspose_pdf_for_python_via_java-24.9.dist-info/RECORD
