Metadata-Version: 2.1
Name: aspose-pdf-for-python-via-java
Version: 24.9
Summary: PDF generation and recognition component. It allows developers to quickly and easily work with creation, edit and conversion functionality to their Python applications.
Author: Aspose
Author-email: marat.khazin@aspose.com
Keywords: aspose,pdf,java
Classifier: Programming Language :: Python :: 3.6
Classifier: License :: Other/Proprietary License
Requires-Python: >=3.6
Requires-Dist: JPype1 ==1.4.1
